freephil/__init__.py
freephil/adapter.py
freephil/cli.py
freephil/command_line.py
freephil/common.py
freephil/converters.py
freephil/experimental.py
freephil/gui_objects.py
freephil/interface.py
freephil/legacy.py
freephil/parser.py
freephil/test_scopes.py
freephil/test_scopes_free.py
freephil/tokenizer.py
freephil/tokens.py
freephil-0.2.1.dist-info/LICENSE
freephil-0.2.1.dist-info/METADATA
freephil-0.2.1.dist-info/WHEEL
freephil-0.2.1.dist-info/entry_points.txt
freephil-0.2.1.dist-info/top_level.txt
freephil-0.2.1.dist-info/RECORD
