Metadata-Version: 2.1
Name: freephil
Version: 0.2.1
Summary: A free command line parsing library
Home-page: UNKNOWN
Author: Markus Gerstel
License: BSD 3-Clause License
Project-URL: Bug-Tracker, https://github.com/Anthchirp/freephil/issues
Project-URL: Documentation, https://freephil.readthedocs.io/en/latest/
Project-URL: GitHub, https://github.com/Anthchirp/freephil
Keywords: dials
Platform: UNKNOWN
Classifier: Development Status :: 4 - Beta
Classifier: License :: OSI Approved :: BSD License
Classifier: Natural Language :: English
Classifier: Programming Language :: Python :: 3
Classifier: Programming Language :: Python :: 3.6
Classifier: Programming Language :: Python :: 3.7
Classifier: Programming Language :: Python :: 3.8
Classifier: Programming Language :: Python :: 3.9
Requires-Python: >=3.6
Requires-Dist: setuptools
